llmtorch/__init__.py
llmtorch/arguments/__init__.py
llmtorch/arguments/arguments_seq2seq_trainer.py
llmtorch/arguments/arguments_trainer.py
llmtorch/data_process/__init__.py
llmtorch/data_process/llm_data_process.py
llmtorch/deeplearning/__init__.py
llmtorch/deeplearning/main_dl_torch.py
llmtorch/trainer/__init__.py
llmtorch/trainer/kerascallbacks.py
llmtorch/trainer/llmmodel.py
llmtorch/trainer/model_seq2seqtrainer.py
llmtorch/trainer/model_trainer.py
llmtorch/trainer/pbar.py
llmtorch/trainer/utils.py
llmtorch-1.0.22.dist-info/LICENSE.txt
llmtorch-1.0.22.dist-info/METADATA
llmtorch-1.0.22.dist-info/WHEEL
llmtorch-1.0.22.dist-info/top_level.txt
llmtorch-1.0.22.dist-info/RECORD
