Metadata-Version: 2.1
Name: llmtorch
Version: 1.0.22
Summary: llm model process for pytorch
Home-page: 
Author: llmtorch team
Author-email: 1027763372@qq.com
License: BSD License
Keywords: machine-learning,deep-learning,ML,DL,pytorch,torch,llm
Platform: all
Classifier: Intended Audience :: Developers
Classifier: Operating System :: OS Independent
Classifier: Natural Language :: Chinese (Simplified)
Classifier: Programming Language :: Python
Classifier: Programming Language :: Python :: 2.7
Classifier: Programming Language :: Python :: 3
Classifier: Programming Language :: Python :: 3.5
Classifier: Programming Language :: Python :: 3.6
Classifier: Programming Language :: Python :: 3.7
Classifier: Programming Language :: Python :: 3.8
Classifier: Topic :: Software Development :: Libraries
License-File: LICENSE.txt
Requires-Dist: torch (>=1.9.0)
Requires-Dist: torchtext
Requires-Dist: tiktoken
Requires-Dist: tqdm
